sch/__init__.py
sch/avatar/__init__.py
sch/avatar/constants.py
sch/avatar/enum.py
sch/avatar/generator.py
sch/compress/__init__.py
sch/compress/bzip.py
sch/compress/compress.py
sch/compress/gzip.py
sch/compress/lzma.py
sch/config/__init__.py
sch/config/config.py
sch/config/convert.py
sch/config/enum.py
sch/db/__init__.py
sch/db/constants.py
sch/db/database.py
sch/db/mysql.py
sch/db/sqlite.py
sch/i18n/__init__.py
sch/i18n/build.py
sch/i18n/i18n.py
sch/image_api/__init__.py
sch/image_api/base_image.py
sch/image_api/constants.py
sch/image_api/exception.py
sch/image_api/lsky.py
sch/interval/__init__.py
sch/interval/run_interval.py
sch/led_control/__init__.py
sch/led_control/led.py
sch/logger/__init__.py
sch/logger/config.py
sch/logger/logger.py
sch/openlist/__init__.py
sch/openlist/model.py
sch/openlist/openlist.py
sch/openlist/user.py
sch/s3/__init__.py
sch/s3/s3.py
sch/util/__init__.py
sch/util/base64.py
sch/util/clip.py
sch/util/ip.py
sch/util/mac.py
sch/util/mac_table.py
sch/util/markdown.py
sch/util/mermaid.py
sch/util/password.py
sch/util/qrcode.py
sch_lib-1.1.1.dist-info/licenses/LICENSE
sch_lib-1.1.1.dist-info/METADATA
sch_lib-1.1.1.dist-info/WHEEL
sch_lib-1.1.1.dist-info/entry_points.txt
sch_lib-1.1.1.dist-info/top_level.txt
sch_lib-1.1.1.dist-info/RECORD
