Metadata-Version: 2.4
Name: sch-lib
Version: 1.1.1
Summary: 轻松使用Python进行开发
Requires-Python: >=3.9
License-File: LICENSE
Requires-Dist: cryptography>=46.0.3
Requires-Dist: pyyaml>=6.0.2
Requires-Dist: toml>=0.10.2
Provides-Extra: db
Requires-Dist: pymysql>=1.1.1; extra == "db"
Requires-Dist: sqlalchemy>=2.0.43; extra == "db"
Provides-Extra: s3
Requires-Dist: boto3>=1.40.10; extra == "s3"
Provides-Extra: image
Requires-Dist: pillow>=11.3.0; extra == "image"
Provides-Extra: qrcode
Requires-Dist: qrcode>=8.2; extra == "qrcode"
Provides-Extra: request
Requires-Dist: bs4>=0.0.2; extra == "request"
Requires-Dist: requests>=2.32.4; extra == "request"
Requires-Dist: fake-useragent>=2.2.0; extra == "request"
Provides-Extra: clip
Requires-Dist: pyperclip>=1.9.0; extra == "clip"
Provides-Extra: markdown
Requires-Dist: markdown>=3.9; extra == "markdown"
Requires-Dist: markdownify>=1.2.0; extra == "markdown"
Provides-Extra: all
Requires-Dist: pymysql>=1.1.1; extra == "all"
Requires-Dist: sqlalchemy>=2.0.43; extra == "all"
Requires-Dist: boto3>=1.40.10; extra == "all"
Requires-Dist: pillow>=11.3.0; extra == "all"
Requires-Dist: qrcode>=8.2; extra == "all"
Requires-Dist: bs4>=0.0.2; extra == "all"
Requires-Dist: requests>=2.32.4; extra == "all"
Requires-Dist: fake-useragent>=2.2.0; extra == "all"
Requires-Dist: pyperclip>=1.9.0; extra == "all"
Requires-Dist: markdown>=3.9; extra == "all"
Requires-Dist: markdownify>=1.2.0; extra == "all"
Dynamic: license-file
